{
  "openapi": "3.0.3",
  "info": {
    "title": "API Documentation",
    "version": "1.0.0",
    "description": "API documentation for the Click Proposta v1.0.0"
  },
  "components": {
    "securitySchemes": {
      "bearerAuth": {
        "type": "http",
        "scheme": "bearer",
        "bearerFormat": "JWT"
      }
    },
    "schemas": {}
  },
  "paths": {
    "/user/customer/create": {
      "post": {
        "operationId": "createNewCustomer",
        "tags": [
          "Customers"
        ],
        "requestBody": {
          "content": {
            "application/json": {
              "schema": {
                "type": "object",
                "properties": {
                  "name": {
                    "type": "string",
                    "minLength": 2,
                    "maxLength": 100
                  },
                  "email": {
                    "type": "string",
                    "format": "email",
                    "pattern": "^(?!\\.)(?!.*\\.\\.)([A-Za-z0-9_'+\\-\\.]*)[A-Za-z0-9_+-]@([A-Za-z0-9][A-Za-z0-9\\-]*\\.)+[A-Za-z]{2,}$"
                  },
                  "phone": {
                    "type": "string",
                    "minLength": 10,
                    "maxLength": 12,
                    "pattern": "^\\d+$"
                  }
                },
                "required": [
                  "name",
                  "email",
                  "phone"
                ]
              }
            }
          },
          "required": true
        },
        "responses": {
          "201": {
            "description": "Default Response",
            "content": {
              "application/json": {
                "schema": {
                  "type": "object",
                  "properties": {
                    "message": {
                      "type": "string"
                    },
                    "statusCode": {
                      "default": 201,
                      "type": "number"
                    }
                  },
                  "required": [
                    "message",
                    "statusCode"
                  ],
                  "additionalProperties": false
                }
              }
            }
          },
          "400": {
            "description": "Default Response",
            "content": {
              "application/json": {
                "schema": {
                  "type": "object",
                  "properties": {
                    "message": {
                      "type": "string"
                    },
                    "statusCode": {
                      "default": 400,
                      "type": "number"
                    }
                  },
                  "required": [
                    "message",
                    "statusCode"
                  ],
                  "additionalProperties": false
                }
              }
            }
          }
        }
      }
    },
    "/user/customers": {
      "get": {
        "operationId": "fetchCustomers",
        "tags": [
          "Customers"
        ],
        "responses": {
          "200": {
            "description": "Default Response",
            "content": {
              "application/json": {
                "schema": {
                  "type": "object",
                  "properties": {
                    "customers": {
                      "type": "array",
                      "items": {
                        "type": "object",
                        "properties": {
                          "name": {
                            "type": "string"
                          },
                          "id": {
                            "type": "string"
                          },
                          "email": {
                            "type": "string"
                          },
                          "phone": {
                            "type": "string"
                          }
                        },
                        "required": [
                          "name",
                          "id",
                          "email",
                          "phone"
                        ],
                        "additionalProperties": false
                      }
                    },
                    "statusCode": {
                      "default": 200,
                      "type": "number"
                    }
                  },
                  "required": [
                    "customers",
                    "statusCode"
                  ],
                  "additionalProperties": false
                }
              }
            }
          },
          "404": {
            "description": "Default Response",
            "content": {
              "application/json": {
                "schema": {
                  "type": "object",
                  "properties": {
                    "message": {
                      "type": "string"
                    },
                    "statusCode": {
                      "default": 404,
                      "type": "number"
                    }
                  },
                  "required": [
                    "message",
                    "statusCode"
                  ],
                  "additionalProperties": false
                }
              }
            }
          }
        }
      }
    },
    "/search-by-name-email": {
      "get": {
        "operationId": "searchByNameEmail",
        "tags": [
          "Customers"
        ],
        "parameters": [
          {
            "schema": {
              "type": "string"
            },
            "in": "query",
            "name": "search",
            "required": true
          }
        ],
        "responses": {
          "200": {
            "description": "Default Response",
            "content": {
              "application/json": {
                "schema": {
                  "type": "object",
                  "properties": {
                    "customers": {
                      "type": "array",
                      "items": {
                        "type": "object",
                        "properties": {
                          "id": {
                            "type": "string",
                            "format": "uuid",
                            "pattern": "^([0-9a-fA-F]{8}-[0-9a-fA-F]{4}-[1-8][0-9a-fA-F]{3}-[89abAB][0-9a-fA-F]{3}-[0-9a-fA-F]{12}|00000000-0000-0000-0000-000000000000|ffffffff-ffff-ffff-ffff-ffffffffffff)$"
                          },
                          "name": {
                            "type": "string",
                            "minLength": 2,
                            "maxLength": 100
                          },
                          "email": {
                            "type": "string",
                            "format": "email",
                            "pattern": "^(?!\\.)(?!.*\\.\\.)([A-Za-z0-9_'+\\-\\.]*)[A-Za-z0-9_+-]@([A-Za-z0-9][A-Za-z0-9\\-]*\\.)+[A-Za-z]{2,}$"
                          },
                          "phone": {
                            "type": "string",
                            "minLength": 10,
                            "maxLength": 15
                          },
                          "createdAt": {
                            "type": "string",
                            "format": "date-time"
                          },
                          "updatedAt": {
                            "type": "string",
                            "format": "date-time"
                          }
                        },
                        "required": [
                          "id",
                          "name",
                          "email",
                          "phone",
                          "createdAt",
                          "updatedAt"
                        ],
                        "additionalProperties": false
                      }
                    }
                  },
                  "required": [
                    "customers"
                  ],
                  "additionalProperties": false
                }
              }
            }
          },
          "404": {
            "description": "Default Response",
            "content": {
              "application/json": {
                "schema": {
                  "type": "object",
                  "properties": {
                    "message": {
                      "type": "string"
                    }
                  },
                  "required": [
                    "message"
                  ],
                  "additionalProperties": false
                }
              }
            }
          },
          "500": {
            "description": "Default Response",
            "content": {
              "application/json": {
                "schema": {
                  "type": "object",
                  "properties": {
                    "message": {
                      "type": "string"
                    }
                  },
                  "required": [
                    "message"
                  ],
                  "additionalProperties": false
                }
              }
            }
          }
        }
      }
    },
    "/complete-register": {
      "patch": {
        "operationId": "completeRegister",
        "tags": [
          "Users"
        ],
        "requestBody": {
          "content": {
            "application/json": {
              "schema": {
                "type": "object",
                "properties": {
                  "phone": {
                    "type": "string",
                    "minLength": 10,
                    "maxLength": 11
                  },
                  "cpf": {
                    "type": "string",
                    "minLength": 11,
                    "maxLength": 11
                  },
                  "cnpj": {
                    "type": "string",
                    "minLength": 14,
                    "maxLength": 18
                  },
                  "street": {
                    "type": "string"
                  },
                  "number": {
                    "type": "string"
                  },
                  "neighborhood": {
                    "type": "string"
                  },
                  "city": {
                    "type": "string"
                  }
                },
                "required": [
                  "phone",
                  "cpf",
                  "street",
                  "number",
                  "neighborhood",
                  "city"
                ]
              }
            }
          },
          "required": true
        },
        "responses": {
          "204": {
            "description": "Default Response",
            "content": {
              "application/json": {
                "schema": {}
              }
            }
          },
          "406": {
            "description": "Default Response",
            "content": {
              "application/json": {
                "schema": {
                  "type": "object",
                  "properties": {
                    "message": {
                      "type": "string"
                    }
                  },
                  "required": [
                    "message"
                  ],
                  "additionalProperties": false
                }
              }
            }
          },
          "409": {
            "description": "Default Response",
            "content": {
              "application/json": {
                "schema": {
                  "type": "object",
                  "properties": {
                    "message": {
                      "type": "string"
                    }
                  },
                  "required": [
                    "message"
                  ],
                  "additionalProperties": false
                }
              }
            }
          },
          "500": {
            "description": "Default Response",
            "content": {
              "application/json": {
                "schema": {
                  "type": "object",
                  "properties": {
                    "message": {
                      "type": "string"
                    }
                  },
                  "required": [
                    "message"
                  ],
                  "additionalProperties": false
                }
              }
            }
          }
        }
      }
    },
    "/is-complete-register": {
      "get": {
        "operationId": "getCompleteRegister",
        "tags": [
          "Users"
        ],
        "responses": {
          "200": {
            "description": "Default Response",
            "content": {
              "application/json": {
                "schema": {
                  "type": "object",
                  "properties": {
                    "isRegisterComplete": {
                      "type": "boolean"
                    }
                  },
                  "additionalProperties": false
                }
              }
            }
          },
          "404": {
            "description": "Default Response",
            "content": {
              "application/json": {
                "schema": {
                  "type": "object",
                  "properties": {
                    "message": {
                      "type": "string"
                    }
                  },
                  "required": [
                    "message"
                  ],
                  "additionalProperties": false
                }
              }
            }
          },
          "500": {
            "description": "Default Response",
            "content": {
              "application/json": {
                "schema": {
                  "type": "object",
                  "properties": {
                    "message": {
                      "type": "string"
                    },
                    "error": {
                      "type": "string"
                    }
                  },
                  "required": [
                    "message"
                  ],
                  "additionalProperties": false
                }
              }
            }
          }
        }
      }
    },
    "/data-for-payment": {
      "get": {
        "operationId": "getDataForPayment",
        "tags": [
          "Users"
        ],
        "responses": {
          "200": {
            "description": "Default Response",
            "content": {
              "application/json": {
                "schema": {
                  "type": "object",
                  "properties": {
                    "name": {
                      "type": "string"
                    },
                    "email": {
                      "type": "string"
                    },
                    "phone": {
                      "type": "string"
                    },
                    "cpf": {
                      "type": "string"
                    }
                  },
                  "required": [
                    "name",
                    "email",
                    "phone",
                    "cpf"
                  ],
                  "additionalProperties": false
                }
              }
            }
          },
          "404": {
            "description": "Default Response",
            "content": {
              "application/json": {
                "schema": {
                  "type": "object",
                  "properties": {
                    "message": {
                      "type": "string"
                    }
                  },
                  "required": [
                    "message"
                  ],
                  "additionalProperties": false
                }
              }
            }
          },
          "422": {
            "description": "Default Response",
            "content": {
              "application/json": {
                "schema": {
                  "type": "object",
                  "properties": {
                    "message": {
                      "type": "string"
                    }
                  },
                  "required": [
                    "message"
                  ],
                  "additionalProperties": false
                }
              }
            }
          },
          "500": {
            "description": "Default Response",
            "content": {
              "application/json": {
                "schema": {
                  "type": "object",
                  "properties": {
                    "message": {
                      "type": "string"
                    }
                  },
                  "required": [
                    "message"
                  ],
                  "additionalProperties": false
                }
              }
            }
          }
        }
      }
    },
    "/me": {
      "get": {
        "operationId": "getMe",
        "tags": [
          "Users"
        ],
        "responses": {
          "200": {
            "description": "Default Response",
            "content": {
              "application/json": {
                "schema": {
                  "type": "object",
                  "properties": {
                    "user": {
                      "type": "object",
                      "properties": {
                        "id": {
                          "type": "string"
                        },
                        "email": {
                          "type": "string",
                          "format": "email",
                          "pattern": "^(?!\\.)(?!.*\\.\\.)([A-Za-z0-9_'+\\-\\.]*)[A-Za-z0-9_+-]@([A-Za-z0-9][A-Za-z0-9\\-]*\\.)+[A-Za-z]{2,}$"
                        },
                        "name": {
                          "anyOf": [
                            {
                              "type": "string"
                            },
                            {
                              "nullable": true,
                              "enum": [
                                null
                              ]
                            }
                          ]
                        },
                        "avatarUrl": {
                          "anyOf": [
                            {
                              "type": "string"
                            },
                            {
                              "nullable": true,
                              "enum": [
                                null
                              ]
                            }
                          ]
                        },
                        "plan": {
                          "type": "string",
                          "enum": [
                            "FREE",
                            "PRO"
                          ]
                        },
                        "isRegisterComplete": {
                          "type": "boolean"
                        }
                      },
                      "required": [
                        "id",
                        "email",
                        "name",
                        "avatarUrl",
                        "plan",
                        "isRegisterComplete"
                      ],
                      "additionalProperties": false
                    }
                  },
                  "required": [
                    "user"
                  ],
                  "additionalProperties": false
                }
              }
            }
          },
          "404": {
            "description": "Default Response",
            "content": {
              "application/json": {
                "schema": {
                  "type": "object",
                  "properties": {
                    "message": {
                      "type": "string"
                    }
                  },
                  "required": [
                    "message"
                  ],
                  "additionalProperties": false
                }
              }
            }
          },
          "500": {
            "description": "Default Response",
            "content": {
              "application/json": {
                "schema": {
                  "type": "object",
                  "properties": {
                    "message": {
                      "type": "string"
                    }
                  },
                  "required": [
                    "message"
                  ],
                  "additionalProperties": false
                }
              }
            }
          }
        }
      }
    },
    "/service": {
      "post": {
        "operationId": "createService",
        "tags": [
          "Services"
        ],
        "requestBody": {
          "content": {
            "application/json": {
              "schema": {
                "type": "object",
                "properties": {
                  "name": {
                    "type": "string"
                  },
                  "description": {
                    "type": "string"
                  }
                },
                "required": [
                  "name"
                ]
              }
            }
          },
          "required": true
        },
        "responses": {
          "201": {
            "description": "Default Response",
            "content": {
              "application/json": {
                "schema": {
                  "type": "object",
                  "properties": {
                    "message": {
                      "type": "string"
                    },
                    "statusCode": {
                      "default": 201,
                      "type": "number"
                    }
                  },
                  "required": [
                    "message",
                    "statusCode"
                  ],
                  "additionalProperties": false
                }
              }
            }
          },
          "500": {
            "description": "Default Response",
            "content": {
              "application/json": {
                "schema": {
                  "type": "object",
                  "properties": {
                    "message": {
                      "type": "string"
                    },
                    "statusCode": {
                      "default": 500,
                      "type": "number"
                    }
                  },
                  "required": [
                    "message",
                    "statusCode"
                  ],
                  "additionalProperties": false
                }
              }
            }
          }
        }
      }
    },
    "/services": {
      "get": {
        "operationId": "fetchManyServices",
        "tags": [
          "Services"
        ],
        "responses": {
          "200": {
            "description": "Default Response",
            "content": {
              "application/json": {
                "schema": {
                  "type": "object",
                  "properties": {
                    "services": {
                      "type": "array",
                      "items": {
                        "type": "object",
                        "properties": {
                          "id": {
                            "type": "string"
                          },
                          "name": {
                            "type": "string"
                          },
                          "description": {
                            "anyOf": [
                              {
                                "type": "string"
                              },
                              {
                                "nullable": true,
                                "enum": [
                                  null
                                ]
                              }
                            ]
                          }
                        },
                        "required": [
                          "id",
                          "name",
                          "description"
                        ],
                        "additionalProperties": false
                      }
                    },
                    "statusCode": {
                      "default": 200,
                      "type": "number"
                    }
                  },
                  "required": [
                    "services",
                    "statusCode"
                  ],
                  "additionalProperties": false
                }
              }
            }
          },
          "500": {
            "description": "Default Response",
            "content": {
              "application/json": {
                "schema": {
                  "type": "object",
                  "properties": {
                    "message": {
                      "type": "string"
                    },
                    "statusCode": {
                      "default": 500,
                      "type": "number"
                    }
                  },
                  "required": [
                    "message",
                    "statusCode"
                  ],
                  "additionalProperties": false
                }
              }
            }
          }
        }
      }
    },
    "/services/{idService}": {
      "delete": {
        "operationId": "deleteService",
        "tags": [
          "Services"
        ],
        "parameters": [
          {
            "schema": {
              "type": "string",
              "format": "uuid",
              "pattern": "^([0-9a-fA-F]{8}-[0-9a-fA-F]{4}-[1-8][0-9a-fA-F]{3}-[89abAB][0-9a-fA-F]{3}-[0-9a-fA-F]{12}|00000000-0000-0000-0000-000000000000|ffffffff-ffff-ffff-ffff-ffffffffffff)$"
            },
            "in": "path",
            "name": "idService",
            "required": true
          }
        ],
        "responses": {
          "200": {
            "description": "Default Response",
            "content": {
              "application/json": {
                "schema": {
                  "type": "object",
                  "properties": {
                    "statusCode": {
                      "default": 200,
                      "type": "number"
                    }
                  },
                  "required": [
                    "statusCode"
                  ],
                  "additionalProperties": false
                }
              }
            }
          },
          "500": {
            "description": "Default Response",
            "content": {
              "application/json": {
                "schema": {
                  "type": "object",
                  "properties": {
                    "message": {
                      "type": "string"
                    },
                    "statusCode": {
                      "default": 500,
                      "type": "number"
                    }
                  },
                  "required": [
                    "message",
                    "statusCode"
                  ],
                  "additionalProperties": false
                }
              }
            }
          }
        }
      },
      "put": {
        "operationId": "updateService",
        "tags": [
          "Services"
        ],
        "requestBody": {
          "content": {
            "application/json": {
              "schema": {
                "type": "object",
                "properties": {
                  "name": {
                    "type": "string"
                  },
                  "description": {
                    "type": "string"
                  }
                }
              }
            }
          }
        },
        "parameters": [
          {
            "schema": {
              "type": "string",
              "format": "uuid",
              "pattern": "^([0-9a-fA-F]{8}-[0-9a-fA-F]{4}-[1-8][0-9a-fA-F]{3}-[89abAB][0-9a-fA-F]{3}-[0-9a-fA-F]{12}|00000000-0000-0000-0000-000000000000|ffffffff-ffff-ffff-ffff-ffffffffffff)$"
            },
            "in": "path",
            "name": "idService",
            "required": true
          }
        ],
        "responses": {
          "200": {
            "description": "Default Response",
            "content": {
              "application/json": {
                "schema": {
                  "type": "object",
                  "properties": {
                    "statusCode": {
                      "default": 200,
                      "type": "number"
                    }
                  },
                  "required": [
                    "statusCode"
                  ],
                  "additionalProperties": false
                }
              }
            }
          },
          "500": {
            "description": "Default Response",
            "content": {
              "application/json": {
                "schema": {
                  "type": "object",
                  "properties": {
                    "message": {
                      "type": "string"
                    },
                    "statusCode": {
                      "default": 500,
                      "type": "number"
                    }
                  },
                  "required": [
                    "message",
                    "statusCode"
                  ],
                  "additionalProperties": false
                }
              }
            }
          }
        }
      }
    },
    "/proposal": {
      "post": {
        "operationId": "createProposal",
        "tags": [
          "Proposals"
        ],
        "requestBody": {
          "content": {
            "application/json": {
              "schema": {
                "type": "object",
                "properties": {
                  "urlLogoImage": {
                    "anyOf": [
                      {
                        "type": "string",
                        "format": "uri"
                      },
                      {
                        "nullable": true,
                        "enum": [
                          null
                        ]
                      }
                    ]
                  },
                  "title": {
                    "type": "string",
                    "minLength": 1,
                    "maxLength": 255
                  },
                  "customersId": {
                    "type": "string",
                    "format": "uuid",
                    "pattern": "^([0-9a-fA-F]{8}-[0-9a-fA-F]{4}-[1-8][0-9a-fA-F]{3}-[89abAB][0-9a-fA-F]{3}-[0-9a-fA-F]{12}|00000000-0000-0000-0000-000000000000|ffffffff-ffff-ffff-ffff-ffffffffffff)$"
                  },
                  "welcomeDescription": {
                    "type": "string",
                    "minLength": 1
                  },
                  "whyUs": {
                    "type": "string",
                    "minLength": 1
                  },
                  "challenge": {
                    "type": "string",
                    "minLength": 1
                  },
                  "solution": {
                    "type": "string",
                    "minLength": 1
                  },
                  "services": {
                    "minItems": 1,
                    "type": "array",
                    "items": {
                      "type": "object",
                      "properties": {
                        "price": {
                          "type": "number",
                          "exclusiveMinimum": true,
                          "minimum": 0
                        },
                        "servicesId": {
                          "type": "string",
                          "format": "uuid",
                          "pattern": "^([0-9a-fA-F]{8}-[0-9a-fA-F]{4}-[1-8][0-9a-fA-F]{3}-[89abAB][0-9a-fA-F]{3}-[0-9a-fA-F]{12}|00000000-0000-0000-0000-000000000000|ffffffff-ffff-ffff-ffff-ffffffffffff)$"
                        }
                      },
                      "required": [
                        "price",
                        "servicesId"
                      ]
                    }
                  },
                  "results": {
                    "type": "string",
                    "minLength": 1
                  },
                  "discount": {
                    "type": "number",
                    "minimum": 0,
                    "maximum": 100
                  }
                },
                "required": [
                  "urlLogoImage",
                  "title",
                  "customersId",
                  "welcomeDescription",
                  "whyUs",
                  "challenge",
                  "solution",
                  "services",
                  "results",
                  "discount"
                ]
              }
            }
          },
          "required": true
        },
        "responses": {
          "200": {
            "description": "Default Response"
          }
        }
      }
    },
    "/proposals/minimal-details": {
      "get": {
        "operationId": "fetchMinimalDetailsProposal",
        "tags": [
          "Proposals"
        ],
        "responses": {
          "200": {
            "description": "Default Response",
            "content": {
              "application/json": {
                "schema": {
                  "type": "array",
                  "items": {
                    "type": "object",
                    "properties": {
                      "id": {
                        "type": "string",
                        "format": "uuid",
                        "pattern": "^([0-9a-fA-F]{8}-[0-9a-fA-F]{4}-[1-8][0-9a-fA-F]{3}-[89abAB][0-9a-fA-F]{3}-[0-9a-fA-F]{12}|00000000-0000-0000-0000-000000000000|ffffffff-ffff-ffff-ffff-ffffffffffff)$"
                      },
                      "name": {
                        "type": "string",
                        "minLength": 2,
                        "maxLength": 100
                      },
                      "title": {
                        "type": "string",
                        "minLength": 2,
                        "maxLength": 100
                      },
                      "totalPrice": {
                        "type": "string"
                      },
                      "status": {
                        "type": "string",
                        "enum": [
                          "DRAFT",
                          "SENT",
                          "APPROVED",
                          "REJECTED"
                        ]
                      }
                    },
                    "required": [
                      "id",
                      "name",
                      "title",
                      "totalPrice",
                      "status"
                    ],
                    "additionalProperties": false
                  }
                }
              }
            }
          },
          "500": {
            "description": "Default Response",
            "content": {
              "application/json": {
                "schema": {
                  "type": "object",
                  "properties": {
                    "message": {
                      "type": "string"
                    }
                  },
                  "required": [
                    "message"
                  ],
                  "additionalProperties": false
                }
              }
            }
          }
        }
      }
    },
    "/proposal/{id}": {
      "get": {
        "operationId": "getProposalById",
        "tags": [
          "Proposals"
        ],
        "parameters": [
          {
            "schema": {
              "type": "string",
              "format": "uuid",
              "pattern": "^([0-9a-fA-F]{8}-[0-9a-fA-F]{4}-[1-8][0-9a-fA-F]{3}-[89abAB][0-9a-fA-F]{3}-[0-9a-fA-F]{12}|00000000-0000-0000-0000-000000000000|ffffffff-ffff-ffff-ffff-ffffffffffff)$"
            },
            "in": "path",
            "name": "id",
            "required": true
          }
        ],
        "responses": {
          "200": {
            "description": "Default Response",
            "content": {
              "application/json": {
                "schema": {
                  "type": "object",
                  "properties": {
                    "id": {
                      "type": "string",
                      "format": "uuid",
                      "pattern": "^([0-9a-fA-F]{8}-[0-9a-fA-F]{4}-[1-8][0-9a-fA-F]{3}-[89abAB][0-9a-fA-F]{3}-[0-9a-fA-F]{12}|00000000-0000-0000-0000-000000000000|ffffffff-ffff-ffff-ffff-ffffffffffff)$"
                    },
                    "title": {
                      "type": "string"
                    },
                    "urlLogoImage": {
                      "anyOf": [
                        {
                          "type": "string"
                        },
                        {
                          "nullable": true,
                          "enum": [
                            null
                          ]
                        }
                      ]
                    },
                    "customersId": {
                      "type": "string"
                    },
                    "welcomeDescription": {
                      "anyOf": [
                        {
                          "type": "string"
                        },
                        {
                          "nullable": true,
                          "enum": [
                            null
                          ]
                        }
                      ]
                    },
                    "whyUs": {
                      "anyOf": [
                        {
                          "type": "string"
                        },
                        {
                          "nullable": true,
                          "enum": [
                            null
                          ]
                        }
                      ]
                    },
                    "challenge": {
                      "anyOf": [
                        {
                          "type": "string"
                        },
                        {
                          "nullable": true,
                          "enum": [
                            null
                          ]
                        }
                      ]
                    },
                    "solution": {
                      "anyOf": [
                        {
                          "type": "string"
                        },
                        {
                          "nullable": true,
                          "enum": [
                            null
                          ]
                        }
                      ]
                    },
                    "results": {
                      "anyOf": [
                        {
                          "type": "string"
                        },
                        {
                          "nullable": true,
                          "enum": [
                            null
                          ]
                        }
                      ]
                    },
                    "discount": {
                      "anyOf": [
                        {
                          "type": "number"
                        },
                        {
                          "nullable": true,
                          "enum": [
                            null
                          ]
                        }
                      ]
                    },
                    "totalPrice": {
                      "anyOf": [
                        {
                          "type": "string"
                        },
                        {
                          "nullable": true,
                          "enum": [
                            null
                          ]
                        }
                      ]
                    },
                    "userId": {
                      "type": "string"
                    },
                    "customerName": {
                      "type": "string"
                    },
                    "services": {
                      "type": "array",
                      "items": {
                        "type": "object",
                        "properties": {
                          "price": {
                            "type": "string"
                          },
                          "name": {
                            "type": "string"
                          }
                        },
                        "required": [
                          "price",
                          "name"
                        ],
                        "additionalProperties": false
                      }
                    }
                  },
                  "required": [
                    "id",
                    "title",
                    "urlLogoImage",
                    "customersId",
                    "welcomeDescription",
                    "whyUs",
                    "challenge",
                    "solution",
                    "results",
                    "discount",
                    "totalPrice",
                    "userId",
                    "customerName",
                    "services"
                  ],
                  "additionalProperties": false
                }
              }
            }
          },
          "500": {
            "description": "Default Response",
            "content": {
              "application/json": {
                "schema": {
                  "type": "object",
                  "properties": {
                    "error": {
                      "type": "string"
                    }
                  },
                  "required": [
                    "error"
                  ],
                  "additionalProperties": false
                }
              }
            }
          }
        }
      }
    },
    "/proposal/{proposalId}": {
      "patch": {
        "operationId": "updateProposal",
        "tags": [
          "Proposals"
        ],
        "requestBody": {
          "content": {
            "application/json": {
              "schema": {
                "type": "object",
                "properties": {
                  "title": {
                    "type": "string"
                  },
                  "welcomeDescription": {
                    "anyOf": [
                      {
                        "type": "string"
                      },
                      {
                        "nullable": true,
                        "enum": [
                          null
                        ]
                      }
                    ]
                  },
                  "whyUs": {
                    "anyOf": [
                      {
                        "type": "string"
                      },
                      {
                        "nullable": true,
                        "enum": [
                          null
                        ]
                      }
                    ]
                  },
                  "challenge": {
                    "anyOf": [
                      {
                        "type": "string"
                      },
                      {
                        "nullable": true,
                        "enum": [
                          null
                        ]
                      }
                    ]
                  },
                  "solution": {
                    "anyOf": [
                      {
                        "type": "string"
                      },
                      {
                        "nullable": true,
                        "enum": [
                          null
                        ]
                      }
                    ]
                  },
                  "results": {
                    "anyOf": [
                      {
                        "type": "string"
                      },
                      {
                        "nullable": true,
                        "enum": [
                          null
                        ]
                      }
                    ]
                  },
                  "discount": {
                    "type": "number"
                  },
                  "totalPrice": {
                    "type": "number"
                  }
                }
              }
            }
          }
        },
        "parameters": [
          {
            "schema": {
              "type": "string",
              "format": "uuid",
              "pattern": "^([0-9a-fA-F]{8}-[0-9a-fA-F]{4}-[1-8][0-9a-fA-F]{3}-[89abAB][0-9a-fA-F]{3}-[0-9a-fA-F]{12}|00000000-0000-0000-0000-000000000000|ffffffff-ffff-ffff-ffff-ffffffffffff)$"
            },
            "in": "path",
            "name": "proposalId",
            "required": true
          }
        ],
        "responses": {
          "204": {
            "description": "Default Response",
            "content": {
              "application/json": {
                "schema": {}
              }
            }
          },
          "400": {
            "description": "Default Response",
            "content": {
              "application/json": {
                "schema": {
                  "type": "object",
                  "properties": {
                    "message": {
                      "type": "string"
                    }
                  },
                  "required": [
                    "message"
                  ],
                  "additionalProperties": false
                }
              }
            }
          },
          "500": {
            "description": "Default Response",
            "content": {
              "application/json": {
                "schema": {
                  "type": "object",
                  "properties": {
                    "message": {
                      "type": "string"
                    }
                  },
                  "required": [
                    "message"
                  ],
                  "additionalProperties": false
                }
              }
            }
          }
        }
      }
    },
    "/proposal/confirm-sending/{proposalId}": {
      "patch": {
        "operationId": "confirmSendingProposal",
        "tags": [
          "Proposals"
        ],
        "parameters": [
          {
            "schema": {
              "type": "string",
              "format": "uuid",
              "pattern": "^([0-9a-fA-F]{8}-[0-9a-fA-F]{4}-[1-8][0-9a-fA-F]{3}-[89abAB][0-9a-fA-F]{3}-[0-9a-fA-F]{12}|00000000-0000-0000-0000-000000000000|ffffffff-ffff-ffff-ffff-ffffffffffff)$"
            },
            "in": "path",
            "name": "proposalId",
            "required": true
          }
        ],
        "responses": {
          "204": {
            "description": "Default Response",
            "content": {
              "application/json": {
                "schema": {
                  "type": "object",
                  "properties": {
                    "statusCode": {
                      "default": 204,
                      "type": "number"
                    }
                  },
                  "required": [
                    "statusCode"
                  ],
                  "additionalProperties": false
                }
              }
            }
          },
          "500": {
            "description": "Default Response",
            "content": {
              "application/json": {
                "schema": {
                  "type": "object",
                  "properties": {
                    "error": {
                      "type": "string"
                    }
                  },
                  "required": [
                    "error"
                  ],
                  "additionalProperties": false
                }
              }
            }
          }
        }
      }
    },
    "/proposal/approve-proposal/{proposalId}": {
      "patch": {
        "operationId": "approveProposal",
        "tags": [
          "Proposals"
        ],
        "parameters": [
          {
            "schema": {
              "type": "string",
              "format": "uuid",
              "pattern": "^([0-9a-fA-F]{8}-[0-9a-fA-F]{4}-[1-8][0-9a-fA-F]{3}-[89abAB][0-9a-fA-F]{3}-[0-9a-fA-F]{12}|00000000-0000-0000-0000-000000000000|ffffffff-ffff-ffff-ffff-ffffffffffff)$"
            },
            "in": "path",
            "name": "proposalId",
            "required": true
          }
        ],
        "responses": {
          "204": {
            "description": "Default Response",
            "content": {
              "application/json": {
                "schema": {
                  "type": "object",
                  "properties": {
                    "statusCode": {
                      "default": 204,
                      "type": "number"
                    }
                  },
                  "required": [
                    "statusCode"
                  ],
                  "additionalProperties": false
                }
              }
            }
          },
          "500": {
            "description": "Default Response",
            "content": {
              "application/json": {
                "schema": {
                  "type": "object",
                  "properties": {
                    "error": {
                      "type": "string"
                    }
                  },
                  "required": [
                    "error"
                  ],
                  "additionalProperties": false
                }
              }
            }
          }
        }
      }
    },
    "/proposals/{id}/recuse": {
      "patch": {
        "operationId": "recuseProposal",
        "tags": [
          "Proposals"
        ],
        "parameters": [
          {
            "schema": {
              "type": "string",
              "format": "uuid",
              "pattern": "^([0-9a-fA-F]{8}-[0-9a-fA-F]{4}-[1-8][0-9a-fA-F]{3}-[89abAB][0-9a-fA-F]{3}-[0-9a-fA-F]{12}|00000000-0000-0000-0000-000000000000|ffffffff-ffff-ffff-ffff-ffffffffffff)$"
            },
            "in": "path",
            "name": "id",
            "required": true
          }
        ],
        "responses": {
          "204": {
            "description": "Default Response",
            "content": {
              "application/json": {
                "schema": {
                  "type": "object",
                  "properties": {
                    "message": {
                      "type": "string"
                    }
                  },
                  "required": [
                    "message"
                  ],
                  "additionalProperties": false
                }
              }
            }
          },
          "404": {
            "description": "Default Response",
            "content": {
              "application/json": {
                "schema": {
                  "type": "object",
                  "properties": {
                    "message": {
                      "type": "string"
                    }
                  },
                  "required": [
                    "message"
                  ],
                  "additionalProperties": false
                }
              }
            }
          },
          "500": {
            "description": "Default Response",
            "content": {
              "application/json": {
                "schema": {
                  "type": "object",
                  "properties": {
                    "message": {
                      "type": "string"
                    }
                  },
                  "required": [
                    "message"
                  ],
                  "additionalProperties": false
                }
              }
            }
          }
        }
      }
    },
    "/customer/{customerId}": {
      "get": {
        "operationId": "getCustomerById",
        "tags": [
          "Customers"
        ],
        "parameters": [
          {
            "schema": {
              "type": "string",
              "format": "uuid",
              "pattern": "^([0-9a-fA-F]{8}-[0-9a-fA-F]{4}-[1-8][0-9a-fA-F]{3}-[89abAB][0-9a-fA-F]{3}-[0-9a-fA-F]{12}|00000000-0000-0000-0000-000000000000|ffffffff-ffff-ffff-ffff-ffffffffffff)$"
            },
            "in": "path",
            "name": "customerId",
            "required": true
          }
        ],
        "responses": {
          "200": {
            "description": "Default Response",
            "content": {
              "application/json": {
                "schema": {
                  "type": "object",
                  "properties": {
                    "customer": {
                      "type": "object",
                      "properties": {
                        "name": {
                          "type": "string"
                        },
                        "email": {
                          "type": "string",
                          "format": "email",
                          "pattern": "^(?!\\.)(?!.*\\.\\.)([A-Za-z0-9_'+\\-\\.]*)[A-Za-z0-9_+-]@([A-Za-z0-9][A-Za-z0-9\\-]*\\.)+[A-Za-z]{2,}$"
                        },
                        "phone": {
                          "type": "string",
                          "minLength": 10,
                          "maxLength": 15
                        },
                        "createdAt": {
                          "type": "string",
                          "format": "date-time"
                        },
                        "updatedAt": {
                          "type": "string",
                          "format": "date-time"
                        }
                      },
                      "required": [
                        "name",
                        "email",
                        "phone",
                        "createdAt",
                        "updatedAt"
                      ],
                      "additionalProperties": false
                    }
                  },
                  "required": [
                    "customer"
                  ],
                  "additionalProperties": false
                }
              }
            }
          },
          "404": {
            "description": "Default Response",
            "content": {
              "application/json": {
                "schema": {
                  "type": "object",
                  "properties": {
                    "message": {
                      "type": "string"
                    }
                  },
                  "required": [
                    "message"
                  ],
                  "additionalProperties": false
                }
              }
            }
          }
        }
      }
    },
    "/payment": {
      "post": {
        "operationId": "createNewPayment",
        "tags": [
          "Payments"
        ],
        "requestBody": {
          "content": {
            "application/json": {
              "schema": {
                "type": "object",
                "properties": {
                  "price": {
                    "default": 2499,
                    "type": "number"
                  },
                  "quantity": {
                    "default": 1,
                    "type": "number"
                  },
                  "customer": {
                    "type": "object",
                    "properties": {
                      "name": {
                        "type": "string",
                        "minLength": 3
                      },
                      "email": {
                        "type": "string",
                        "format": "email",
                        "pattern": "^(?!\\.)(?!.*\\.\\.)([A-Za-z0-9_'+\\-\\.]*)[A-Za-z0-9_+-]@([A-Za-z0-9][A-Za-z0-9\\-]*\\.)+[A-Za-z]{2,}$"
                      },
                      "cellphone": {
                        "type": "string",
                        "minLength": 10,
                        "maxLength": 11
                      },
                      "cpf": {
                        "type": "string",
                        "minLength": 11,
                        "maxLength": 14
                      }
                    },
                    "required": [
                      "name",
                      "email",
                      "cellphone",
                      "cpf"
                    ]
                  }
                },
                "required": [
                  "customer"
                ]
              }
            }
          },
          "required": true
        },
        "responses": {
          "201": {
            "description": "Default Response",
            "content": {
              "application/json": {
                "schema": {
                  "type": "string",
                  "format": "uri"
                }
              }
            }
          },
          "500": {
            "description": "Default Response",
            "content": {
              "application/json": {
                "schema": {
                  "type": "object",
                  "properties": {
                    "message": {
                      "type": "string"
                    }
                  },
                  "required": [
                    "message"
                  ],
                  "additionalProperties": false
                }
              }
            }
          }
        }
      }
    },
    "/confirm-payment": {
      "post": {
        "operationId": "confirmPayment",
        "tags": [
          "Payments"
        ],
        "requestBody": {
          "content": {
            "application/json": {
              "schema": {
                "type": "object",
                "properties": {
                  "data": {
                    "type": "object",
                    "properties": {
                      "billing": {
                        "type": "object",
                        "properties": {
                          "amount": {
                            "type": "number"
                          },
                          "couponsUsed": {
                            "type": "array",
                            "items": {}
                          },
                          "customer": {
                            "type": "object",
                            "properties": {
                              "id": {
                                "type": "string"
                              },
                              "metadata": {
                                "type": "object",
                                "properties": {
                                  "cellphone": {
                                    "type": "string"
                                  },
                                  "email": {
                                    "type": "string"
                                  },
                                  "name": {
                                    "type": "string"
                                  },
                                  "taxId": {
                                    "type": "string"
                                  }
                                },
                                "required": [
                                  "cellphone",
                                  "email",
                                  "name",
                                  "taxId"
                                ]
                              }
                            },
                            "required": [
                              "id",
                              "metadata"
                            ]
                          },
                          "frequency": {
                            "type": "string"
                          },
                          "id": {
                            "type": "string"
                          },
                          "kind": {
                            "type": "array",
                            "items": {
                              "type": "string"
                            }
                          },
                          "paidAmount": {
                            "type": "number"
                          },
                          "products": {
                            "type": "array",
                            "items": {
                              "type": "object",
                              "properties": {
                                "externalId": {
                                  "type": "string"
                                },
                                "publicId": {
                                  "type": "string"
                                },
                                "quantity": {
                                  "type": "number"
                                }
                              },
                              "required": [
                                "externalId",
                                "publicId",
                                "quantity"
                              ]
                            }
                          },
                          "status": {
                            "type": "string"
                          }
                        },
                        "required": [
                          "amount",
                          "couponsUsed",
                          "customer",
                          "frequency",
                          "id",
                          "kind",
                          "paidAmount",
                          "products",
                          "status"
                        ]
                      },
                      "payment": {
                        "type": "object",
                        "properties": {
                          "amount": {
                            "type": "number"
                          },
                          "fee": {
                            "type": "number"
                          },
                          "method": {
                            "type": "string"
                          }
                        },
                        "required": [
                          "amount",
                          "fee",
                          "method"
                        ]
                      }
                    },
                    "required": [
                      "billing",
                      "payment"
                    ]
                  },
                  "devMode": {
                    "type": "boolean"
                  },
                  "event": {
                    "type": "string"
                  }
                },
                "required": [
                  "data",
                  "devMode",
                  "event"
                ]
              }
            }
          },
          "required": true
        },
        "parameters": [
          {
            "schema": {
              "type": "string"
            },
            "in": "query",
            "name": "webhookSecret",
            "required": true
          }
        ],
        "responses": {
          "200": {
            "description": "Default Response"
          }
        }
      }
    },
    "/draft-proposals/{customerId}": {
      "post": {
        "operationId": "createProposalDraft",
        "tags": [
          "DraftProposals"
        ],
        "requestBody": {
          "content": {
            "application/json": {
              "schema": {
                "type": "object",
                "properties": {
                  "userPrompt": {
                    "type": "string",
                    "minLength": 10,
                    "maxLength": 5000
                  }
                },
                "required": [
                  "userPrompt"
                ]
              }
            }
          },
          "required": true
        },
        "parameters": [
          {
            "schema": {
              "type": "string",
              "format": "uuid",
              "pattern": "^([0-9a-fA-F]{8}-[0-9a-fA-F]{4}-[1-8][0-9a-fA-F]{3}-[89abAB][0-9a-fA-F]{3}-[0-9a-fA-F]{12}|00000000-0000-0000-0000-000000000000|ffffffff-ffff-ffff-ffff-ffffffffffff)$"
            },
            "in": "path",
            "name": "customerId",
            "required": true
          }
        ],
        "responses": {
          "201": {
            "description": "Default Response",
            "content": {
              "application/json": {
                "schema": {}
              }
            }
          },
          "404": {
            "description": "Default Response",
            "content": {
              "application/json": {
                "schema": {
                  "type": "object",
                  "properties": {
                    "message": {
                      "type": "string"
                    }
                  },
                  "required": [
                    "message"
                  ],
                  "additionalProperties": false
                }
              }
            }
          },
          "500": {
            "description": "Default Response",
            "content": {
              "application/json": {
                "schema": {
                  "type": "object",
                  "properties": {
                    "message": {
                      "type": "string"
                    }
                  },
                  "required": [
                    "message"
                  ],
                  "additionalProperties": false
                }
              }
            }
          }
        }
      }
    },
    "/draft-proposals/{customerId}/last": {
      "get": {
        "operationId": "getLastDraftProposal",
        "tags": [
          "DraftProposals"
        ],
        "parameters": [
          {
            "schema": {
              "type": "string",
              "format": "uuid",
              "pattern": "^([0-9a-fA-F]{8}-[0-9a-fA-F]{4}-[1-8][0-9a-fA-F]{3}-[89abAB][0-9a-fA-F]{3}-[0-9a-fA-F]{12}|00000000-0000-0000-0000-000000000000|ffffffff-ffff-ffff-ffff-ffffffffffff)$"
            },
            "in": "path",
            "name": "customerId",
            "required": true
          }
        ],
        "responses": {
          "200": {
            "description": "Default Response",
            "content": {
              "application/json": {
                "schema": {
                  "type": "object",
                  "properties": {
                    "proposalDraft": {
                      "type": "object",
                      "properties": {
                        "title": {
                          "type": "string"
                        },
                        "welcomeDescription": {
                          "type": "string"
                        },
                        "whyUs": {
                          "type": "string"
                        },
                        "challenge": {
                          "type": "string"
                        },
                        "solution": {
                          "type": "string"
                        },
                        "results": {
                          "type": "string"
                        }
                      },
                      "required": [
                        "title",
                        "welcomeDescription",
                        "whyUs",
                        "challenge",
                        "solution",
                        "results"
                      ],
                      "additionalProperties": false
                    }
                  },
                  "required": [
                    "proposalDraft"
                  ],
                  "additionalProperties": false
                }
              }
            }
          },
          "404": {
            "description": "Default Response",
            "content": {
              "application/json": {
                "schema": {
                  "type": "object",
                  "properties": {
                    "message": {
                      "type": "string"
                    }
                  },
                  "required": [
                    "message"
                  ],
                  "additionalProperties": false
                }
              }
            }
          },
          "500": {
            "description": "Default Response",
            "content": {
              "application/json": {
                "schema": {
                  "type": "object",
                  "properties": {
                    "message": {
                      "type": "string"
                    }
                  },
                  "required": [
                    "message"
                  ],
                  "additionalProperties": false
                }
              }
            }
          }
        }
      }
    },
    "/pdf/generate": {
      "post": {
        "tags": [
          "PDF"
        ],
        "requestBody": {
          "content": {
            "application/json": {
              "schema": {
                "type": "object",
                "properties": {
                  "imgUrl": {
                    "type": "string"
                  },
                  "nameUser": {
                    "type": "string"
                  },
                  "nameCustomer": {
                    "type": "string"
                  },
                  "emailCustomer": {
                    "type": "string"
                  },
                  "phoneCustomer": {
                    "type": "string"
                  },
                  "total": {
                    "type": "string"
                  },
                  "services": {
                    "type": "array",
                    "items": {
                      "type": "object",
                      "properties": {
                        "id": {
                          "type": "string"
                        },
                        "title": {
                          "type": "string"
                        },
                        "description": {
                          "type": "string"
                        },
                        "quantity": {
                          "anyOf": [
                            {
                              "type": "number"
                            },
                            {
                              "nullable": true,
                              "enum": [
                                null
                              ]
                            }
                          ]
                        },
                        "price": {
                          "anyOf": [
                            {
                              "type": "number"
                            },
                            {
                              "nullable": true,
                              "enum": [
                                null
                              ]
                            }
                          ]
                        },
                        "budgetsId": {
                          "anyOf": [
                            {
                              "type": "string"
                            },
                            {
                              "nullable": true,
                              "enum": [
                                null
                              ]
                            }
                          ]
                        }
                      },
                      "required": [
                        "id",
                        "title",
                        "description",
                        "budgetsId"
                      ]
                    }
                  }
                },
                "required": [
                  "imgUrl",
                  "nameUser",
                  "nameCustomer",
                  "emailCustomer",
                  "phoneCustomer",
                  "total",
                  "services"
                ]
              }
            }
          },
          "required": true
        },
        "responses": {
          "200": {
            "description": "Default Response"
          }
        }
      }
    },
    "/pdf/generate-product": {
      "post": {
        "operationId": "generatePdfProduct",
        "tags": [
          "PDF"
        ],
        "requestBody": {
          "content": {
            "application/json": {
              "schema": {
                "type": "object",
                "properties": {
                  "total": {
                    "type": "string"
                  },
                  "services": {
                    "type": "array",
                    "items": {
                      "type": "object",
                      "properties": {
                        "id": {
                          "type": "string"
                        },
                        "title": {
                          "type": "string"
                        },
                        "description": {
                          "type": "string"
                        },
                        "quantity": {
                          "anyOf": [
                            {
                              "type": "number"
                            },
                            {
                              "nullable": true,
                              "enum": [
                                null
                              ]
                            }
                          ]
                        },
                        "price": {
                          "anyOf": [
                            {
                              "type": "number"
                            },
                            {
                              "nullable": true,
                              "enum": [
                                null
                              ]
                            }
                          ]
                        },
                        "budgetsId": {
                          "anyOf": [
                            {
                              "type": "string"
                            },
                            {
                              "nullable": true,
                              "enum": [
                                null
                              ]
                            }
                          ]
                        }
                      },
                      "required": [
                        "id",
                        "title",
                        "description",
                        "budgetsId"
                      ]
                    }
                  }
                },
                "required": [
                  "total",
                  "services"
                ]
              }
            }
          },
          "required": true
        },
        "responses": {
          "200": {
            "description": "Default Response"
          }
        }
      }
    },
    "/pdf/regenerate/{budgetId}": {
      "get": {
        "operationId": "regeneratePdfDocument",
        "parameters": [
          {
            "schema": {
              "type": "string"
            },
            "in": "path",
            "name": "budgetId",
            "required": true
          }
        ],
        "responses": {
          "200": {
            "description": "Default Response"
          }
        }
      }
    },
    "/budgets": {
      "post": {
        "tags": [
          "Budgets"
        ],
        "requestBody": {
          "content": {
            "application/json": {
              "schema": {
                "type": "object",
                "properties": {
                  "customerId": {
                    "type": "string",
                    "format": "uuid",
                    "pattern": "^([0-9a-fA-F]{8}-[0-9a-fA-F]{4}-[1-8][0-9a-fA-F]{3}-[89abAB][0-9a-fA-F]{3}-[0-9a-fA-F]{12}|00000000-0000-0000-0000-000000000000|ffffffff-ffff-ffff-ffff-ffffffffffff)$"
                  },
                  "userId": {
                    "type": "string",
                    "format": "uuid",
                    "pattern": "^([0-9a-fA-F]{8}-[0-9a-fA-F]{4}-[1-8][0-9a-fA-F]{3}-[89abAB][0-9a-fA-F]{3}-[0-9a-fA-F]{12}|00000000-0000-0000-0000-000000000000|ffffffff-ffff-ffff-ffff-ffffffffffff)$"
                  },
                  "total": {
                    "type": "number"
                  },
                  "services": {
                    "type": "array",
                    "items": {
                      "type": "object",
                      "properties": {
                        "id": {
                          "type": "string"
                        },
                        "title": {
                          "type": "string"
                        },
                        "description": {
                          "type": "string"
                        },
                        "quantity": {
                          "anyOf": [
                            {
                              "type": "number"
                            },
                            {
                              "nullable": true,
                              "enum": [
                                null
                              ]
                            }
                          ]
                        },
                        "price": {
                          "anyOf": [
                            {
                              "type": "number"
                            },
                            {
                              "nullable": true,
                              "enum": [
                                null
                              ]
                            }
                          ]
                        }
                      },
                      "required": [
                        "id",
                        "title",
                        "description"
                      ]
                    }
                  }
                },
                "required": [
                  "customerId",
                  "userId",
                  "total",
                  "services"
                ]
              }
            }
          },
          "required": true
        },
        "responses": {
          "201": {
            "description": "Default Response",
            "content": {
              "application/json": {
                "schema": {}
              }
            }
          },
          "404": {
            "description": "Default Response",
            "content": {
              "application/json": {
                "schema": {
                  "type": "object",
                  "properties": {
                    "message": {
                      "type": "string"
                    }
                  },
                  "required": [
                    "message"
                  ],
                  "additionalProperties": false
                }
              }
            }
          }
        }
      },
      "get": {
        "operationId": "fetchManyBudgets",
        "tags": [
          "Budgets"
        ],
        "parameters": [
          {
            "schema": {
              "default": 0,
              "type": "number"
            },
            "in": "query",
            "name": "pageIndex",
            "required": false
          }
        ],
        "responses": {
          "200": {
            "description": "Default Response",
            "content": {
              "application/json": {
                "schema": {
                  "type": "object",
                  "properties": {
                    "budgets": {
                      "type": "array",
                      "items": {
                        "type": "object",
                        "properties": {
                          "id": {
                            "type": "string"
                          },
                          "total": {
                            "type": "number"
                          },
                          "status": {
                            "type": "string"
                          },
                          "customerName": {
                            "type": "string"
                          }
                        },
                        "required": [
                          "id",
                          "total",
                          "status",
                          "customerName"
                        ],
                        "additionalProperties": false
                      }
                    }
                  },
                  "required": [
                    "budgets"
                  ],
                  "additionalProperties": false
                }
              }
            }
          },
          "404": {
            "description": "Default Response",
            "content": {
              "application/json": {
                "schema": {
                  "type": "object",
                  "properties": {
                    "message": {
                      "type": "string"
                    }
                  },
                  "required": [
                    "message"
                  ],
                  "additionalProperties": false
                }
              }
            }
          }
        }
      }
    },
    "/budgets/{budgetId}": {
      "get": {
        "operationId": "getByIdBudget",
        "tags": [
          "Budgets"
        ],
        "parameters": [
          {
            "schema": {
              "type": "string",
              "format": "uuid",
              "pattern": "^([0-9a-fA-F]{8}-[0-9a-fA-F]{4}-[1-8][0-9a-fA-F]{3}-[89abAB][0-9a-fA-F]{3}-[0-9a-fA-F]{12}|00000000-0000-0000-0000-000000000000|ffffffff-ffff-ffff-ffff-ffffffffffff)$"
            },
            "in": "path",
            "name": "budgetId",
            "required": true
          }
        ],
        "responses": {
          "200": {
            "description": "Default Response",
            "content": {
              "application/json": {
                "schema": {
                  "type": "object",
                  "properties": {
                    "budget": {
                      "type": "object",
                      "properties": {
                        "id": {
                          "type": "string"
                        },
                        "total": {
                          "type": "number"
                        },
                        "status": {
                          "type": "string"
                        },
                        "customersId": {
                          "type": "string"
                        },
                        "createdAt": {
                          "type": "string",
                          "format": "date-time"
                        },
                        "customerName": {
                          "type": "string"
                        },
                        "budgetsServices": {
                          "type": "array",
                          "items": {
                            "type": "object",
                            "properties": {
                              "id": {
                                "type": "string"
                              },
                              "title": {
                                "type": "string"
                              },
                              "description": {
                                "type": "string"
                              },
                              "quantity": {
                                "anyOf": [
                                  {
                                    "type": "number"
                                  },
                                  {
                                    "nullable": true,
                                    "enum": [
                                      null
                                    ]
                                  }
                                ]
                              },
                              "price": {
                                "anyOf": [
                                  {
                                    "type": "number"
                                  },
                                  {
                                    "nullable": true,
                                    "enum": [
                                      null
                                    ]
                                  }
                                ]
                              }
                            },
                            "required": [
                              "id",
                              "title",
                              "description",
                              "quantity",
                              "price"
                            ],
                            "additionalProperties": false
                          }
                        }
                      },
                      "required": [
                        "id",
                        "total",
                        "status",
                        "customersId",
                        "createdAt",
                        "customerName",
                        "budgetsServices"
                      ],
                      "additionalProperties": false
                    }
                  },
                  "required": [
                    "budget"
                  ],
                  "additionalProperties": false
                }
              }
            }
          },
          "404": {
            "description": "Default Response",
            "content": {
              "application/json": {
                "schema": {
                  "type": "object",
                  "properties": {
                    "message": {
                      "type": "string"
                    }
                  },
                  "required": [
                    "message"
                  ],
                  "additionalProperties": false
                }
              }
            }
          }
        }
      }
    },
    "/public/budgets/{budgetId}": {
      "get": {
        "operationId": "getPublicBudget",
        "summary": "Get public budget details",
        "tags": [
          "Budgets"
        ],
        "description": "Fetch budget details for public viewing without authentication.",
        "parameters": [
          {
            "schema": {
              "type": "string",
              "format": "uuid",
              "pattern": "^([0-9a-fA-F]{8}-[0-9a-fA-F]{4}-[1-8][0-9a-fA-F]{3}-[89abAB][0-9a-fA-F]{3}-[0-9a-fA-F]{12}|00000000-0000-0000-0000-000000000000|ffffffff-ffff-ffff-ffff-ffffffffffff)$"
            },
            "in": "path",
            "name": "budgetId",
            "required": true
          }
        ],
        "responses": {
          "200": {
            "description": "Default Response",
            "content": {
              "application/json": {
                "schema": {
                  "type": "object",
                  "properties": {
                    "budget": {
                      "type": "object",
                      "properties": {
                        "id": {
                          "type": "string"
                        },
                        "title": {
                          "type": "string"
                        },
                        "description": {
                          "type": "string"
                        },
                        "total": {
                          "type": "number"
                        },
                        "status": {
                          "type": "string"
                        },
                        "createdAt": {
                          "type": "string",
                          "format": "date-time"
                        },
                        "customer": {
                          "type": "object",
                          "properties": {
                            "name": {
                              "type": "string"
                            }
                          },
                          "required": [
                            "name"
                          ],
                          "additionalProperties": false
                        },
                        "user": {
                          "type": "object",
                          "properties": {
                            "name": {
                              "anyOf": [
                                {
                                  "type": "string"
                                },
                                {
                                  "nullable": true,
                                  "enum": [
                                    null
                                  ]
                                }
                              ]
                            },
                            "avatarUrl": {
                              "anyOf": [
                                {
                                  "type": "string"
                                },
                                {
                                  "nullable": true,
                                  "enum": [
                                    null
                                  ]
                                }
                              ]
                            }
                          },
                          "required": [
                            "name",
                            "avatarUrl"
                          ],
                          "additionalProperties": false
                        },
                        "budgetsServices": {
                          "type": "array",
                          "items": {
                            "type": "object",
                            "properties": {
                              "id": {
                                "type": "string"
                              },
                              "title": {
                                "type": "string"
                              },
                              "description": {
                                "type": "string"
                              },
                              "quantity": {
                                "anyOf": [
                                  {
                                    "type": "number"
                                  },
                                  {
                                    "nullable": true,
                                    "enum": [
                                      null
                                    ]
                                  }
                                ]
                              },
                              "price": {
                                "anyOf": [
                                  {
                                    "type": "number"
                                  },
                                  {
                                    "nullable": true,
                                    "enum": [
                                      null
                                    ]
                                  }
                                ]
                              }
                            },
                            "required": [
                              "id",
                              "title",
                              "description",
                              "quantity",
                              "price"
                            ],
                            "additionalProperties": false
                          }
                        }
                      },
                      "required": [
                        "id",
                        "title",
                        "total",
                        "status",
                        "createdAt",
                        "customer",
                        "user",
                        "budgetsServices"
                      ],
                      "additionalProperties": false
                    }
                  },
                  "required": [
                    "budget"
                  ],
                  "additionalProperties": false
                }
              }
            }
          },
          "404": {
            "description": "Default Response",
            "content": {
              "application/json": {
                "schema": {
                  "type": "object",
                  "properties": {
                    "message": {
                      "type": "string"
                    }
                  },
                  "required": [
                    "message"
                  ],
                  "additionalProperties": false
                }
              }
            }
          }
        }
      }
    }
  },
  "security": [
    {
      "bearerAuth": []
    }
  ]
}